{"schema_version":1,"timestamp_ms":1773709495525,"sequence":909,"detections":[{"class_id":3,"confidence":0.6735,"x_center":0.7096,"y_center":0.4273,"width":0.0112,"height":0.0278,"source_id":0,"frame_num":909,"label":"stop"},{"class_id":0,"confidence":0.5764,"x_center":0.33,"y_center":0.3929,"width":0.0087,"height":0.026,"source_id":0,"frame_num":909,"label":"go"},{"class_id":4,"confidence":0.3317,"x_center":0.4764,"y_center":0.4569,"width":0.0098,"height":0.02,"source_id":0,"frame_num":909,"label":"stopLeft"},{"class_id":4,"confidence":0.2548,"x_center":0.4738,"y_center":0.4569,"width":0.0102,"height":0.0202,"source_id":0,"frame_num":909,"label":"stopLeft"}]}