{"schema_version":1,"timestamp_ms":1773813762606,"sequence":179,"detections":[{"class_id":2,"confidence":0.7392,"x_center":0.3402,"y_center":0.524,"width":0.0735,"height":0.0523,"source_id":0,"frame_num":179,"label":"car","blind_spot":"none","model":"coco"},{"class_id":2,"confidence":0.7042,"x_center":0.6662,"y_center":0.5397,"width":0.0822,"height":0.1112,"source_id":0,"frame_num":179,"label":"car","blind_spot":"none","model":"coco"},{"class_id":2,"confidence":0.5974,"x_center":0.162,"y_center":0.5166,"width":0.1224,"height":0.0923,"source_id":0,"frame_num":179,"label":"car","blind_spot":"left","model":"coco"},{"class_id":2,"confidence":0.5752,"x_center":0.75,"y_center":0.5386,"width":0.0544,"height":0.0542,"source_id":0,"frame_num":179,"label":"car","blind_spot":"none","model":"coco"},{"class_id":7,"confidence":0.5451,"x_center":0.161,"y_center":0.5181,"width":0.1221,"height":0.0917,"source_id":0,"frame_num":179,"label":"truck","blind_spot":"left","model":"coco"}]}