{"schema_version":1,"timestamp_ms":1773710149146,"sequence":1042,"detections":[{"class_id":3,"confidence":0.777,"x_center":0.4828,"y_center":0.3695,"width":0.012,"height":0.0317,"source_id":0,"frame_num":1042,"label":"stop","blind_spot":"none"},{"class_id":0,"confidence":0.7498,"x_center":0.3802,"y_center":0.3827,"width":0.011,"height":0.033,"source_id":0,"frame_num":1042,"label":"go","blind_spot":"none"},{"class_id":3,"confidence":0.5577,"x_center":0.6352,"y_center":0.4556,"width":0.0084,"height":0.0234,"source_id":0,"frame_num":1042,"label":"stop","blind_spot":"none"}]}