{"schema_version":1,"timestamp_ms":1773813778595,"sequence":680,"detections":[{"class_id":0,"confidence":0.2879,"x_center":0.2069,"y_center":0.4582,"width":0.0079,"height":0.0212,"source_id":0,"frame_num":680,"label":"go","blind_spot":"none","model":"lisa"},{"class_id":2,"confidence":0.7839,"x_center":0.732,"y_center":0.5579,"width":0.0909,"height":0.1308,"source_id":0,"frame_num":680,"label":"car","blind_spot":"none","model":"coco"},{"class_id":2,"confidence":0.7535,"x_center":0.825,"y_center":0.5648,"width":0.0914,"height":0.1447,"source_id":0,"frame_num":680,"label":"car","blind_spot":"right","model":"coco"},{"class_id":2,"confidence":0.7211,"x_center":0.6295,"y_center":0.5366,"width":0.0937,"height":0.1122,"source_id":0,"frame_num":680,"label":"car","blind_spot":"none","model":"coco"},{"class_id":2,"confidence":0.5885,"x_center":0.5722,"y_center":0.5225,"width":0.048,"height":0.0488,"source_id":0,"frame_num":680,"label":"car","blind_spot":"none","model":"coco"},{"class_id":2,"confidence":0.5681,"x_center":0.4251,"y_center":0.5187,"width":0.1019,"height":0.1229,"source_id":0,"frame_num":680,"label":"car","blind_spot":"none","model":"coco"},{"class_id":2,"confidence":0.4228,"x_center":0.708,"y_center":0.5274,"width":0.0767,"height":0.0729,"source_id":0,"frame_num":680,"label":"car","blind_spot":"none","model":"coco"},{"class_id":7,"confidence":0.4224,"x_center":0.4244,"y_center":0.5177,"width":0.1018,"height":0.1228,"source_id":0,"frame_num":680,"label":"truck","blind_spot":"none","model":"coco"}]}