{"schema_version":1,"timestamp_ms":1773813761830,"sequence":154,"detections":[{"class_id":2,"confidence":0.7613,"x_center":0.4425,"y_center":0.5197,"width":0.0695,"height":0.0547,"source_id":0,"frame_num":154,"label":"car","blind_spot":"none","model":"coco"},{"class_id":2,"confidence":0.6452,"x_center":0.5564,"y_center":0.5272,"width":0.0486,"height":0.034,"source_id":0,"frame_num":154,"label":"car","blind_spot":"none","model":"coco"},{"class_id":2,"confidence":0.6337,"x_center":0.6558,"y_center":0.5369,"width":0.0818,"height":0.1171,"source_id":0,"frame_num":154,"label":"car","blind_spot":"none","model":"coco"},{"class_id":2,"confidence":0.5035,"x_center":0.7236,"y_center":0.5347,"width":0.0303,"height":0.0435,"source_id":0,"frame_num":154,"label":"car","blind_spot":"none","model":"coco"}]}