{"schema_version":1,"timestamp_ms":1773709483591,"sequence":48,"detections":[{"class_id":0,"confidence":0.8297,"x_center":0.2726,"y_center":0.0441,"width":0.0326,"height":0.0881,"source_id":0,"frame_num":48,"label":"go"},{"class_id":0,"confidence":0.8059,"x_center":0.4616,"y_center":0.0952,"width":0.034,"height":0.1107,"source_id":0,"frame_num":48,"label":"go"},{"class_id":0,"confidence":0.4383,"x_center":0.7583,"y_center":0.2889,"width":0.0314,"height":0.0986,"source_id":0,"frame_num":48,"label":"go"}]}