{"schema_version":1,"timestamp_ms":1773813789249,"sequence":1024,"detections":[{"class_id":3,"confidence":0.7702,"x_center":0.4833,"y_center":0.3945,"width":0.0102,"height":0.0277,"source_id":0,"frame_num":1024,"label":"stop","blind_spot":"none","model":"lisa"},{"class_id":0,"confidence":0.6789,"x_center":0.3918,"y_center":0.4071,"width":0.0099,"height":0.0308,"source_id":0,"frame_num":1024,"label":"go","blind_spot":"none","model":"lisa"},{"class_id":3,"confidence":0.6759,"x_center":0.6193,"y_center":0.4698,"width":0.009,"height":0.0231,"source_id":0,"frame_num":1024,"label":"stop","blind_spot":"none","model":"lisa"},{"class_id":2,"confidence":0.8366,"x_center":0.6854,"y_center":0.6162,"width":0.23,"height":0.2532,"source_id":0,"frame_num":1024,"label":"car","blind_spot":"none","model":"coco"},{"class_id":2,"confidence":0.7191,"x_center":0.8933,"y_center":0.6842,"width":0.2126,"height":0.5237,"source_id":0,"frame_num":1024,"label":"car","blind_spot":"right","model":"coco"},{"class_id":2,"confidence":0.6671,"x_center":0.5007,"y_center":0.9284,"width":0.554,"height":0.1307,"source_id":0,"frame_num":1024,"label":"car","blind_spot":"none","model":"coco"},{"class_id":2,"confidence":0.6433,"x_center":0.2784,"y_center":0.5734,"width":0.1148,"height":0.1897,"source_id":0,"frame_num":1024,"label":"car","blind_spot":"none","model":"coco"},{"class_id":2,"confidence":0.5519,"x_center":0.3536,"y_center":0.5504,"width":0.0353,"height":0.0403,"source_id":0,"frame_num":1024,"label":"car","blind_spot":"none","model":"coco"},{"class_id":7,"confidence":0.4797,"x_center":0.1534,"y_center":0.572,"width":0.1346,"height":0.1808,"source_id":0,"frame_num":1024,"label":"truck","blind_spot":"left","model":"coco"},{"class_id":2,"confidence":0.443,"x_center":0.3827,"y_center":0.5551,"width":0.0296,"height":0.0367,"source_id":0,"frame_num":1024,"label":"car","blind_spot":"none","model":"coco"},{"class_id":2,"confidence":0.4142,"x_center":0.4269,"y_center":0.5543,"width":0.0393,"height":0.0544,"source_id":0,"frame_num":1024,"label":"car","blind_spot":"none","model":"coco"}]}