{"schema_version":1,"timestamp_ms":1773813761580,"sequence":146,"detections":[{"class_id":2,"confidence":0.7495,"x_center":0.6518,"y_center":0.5367,"width":0.0853,"height":0.115,"source_id":0,"frame_num":146,"label":"car","blind_spot":"none","model":"coco"},{"class_id":2,"confidence":0.5289,"x_center":0.5027,"y_center":0.5201,"width":0.0625,"height":0.0469,"source_id":0,"frame_num":146,"label":"car","blind_spot":"none","model":"coco"},{"class_id":2,"confidence":0.4795,"x_center":0.5964,"y_center":0.5275,"width":0.0195,"height":0.0313,"source_id":0,"frame_num":146,"label":"car","blind_spot":"none","model":"coco"},{"class_id":2,"confidence":0.459,"x_center":0.715,"y_center":0.5364,"width":0.0336,"height":0.0432,"source_id":0,"frame_num":146,"label":"car","blind_spot":"none","model":"coco"}]}