{"schema_version":1,"timestamp_ms":1773709497619,"sequence":1052,"detections":[{"class_id":3,"confidence":0.754,"x_center":0.4843,"y_center":0.3551,"width":0.0123,"height":0.0337,"source_id":0,"frame_num":1052,"label":"stop"},{"class_id":3,"confidence":0.6631,"x_center":0.646,"y_center":0.4468,"width":0.0083,"height":0.023,"source_id":0,"frame_num":1052,"label":"stop"},{"class_id":0,"confidence":0.6167,"x_center":0.3754,"y_center":0.369,"width":0.0117,"height":0.0341,"source_id":0,"frame_num":1052,"label":"go"}]}