{"schema_version":1,"timestamp_ms":1773813787761,"sequence":977,"detections":[{"class_id":3,"confidence":0.7701,"x_center":0.5046,"y_center":0.4425,"width":0.0085,"height":0.0236,"source_id":0,"frame_num":977,"label":"stop","blind_spot":"none","model":"lisa"},{"class_id":0,"confidence":0.482,"x_center":0.4357,"y_center":0.451,"width":0.0089,"height":0.0245,"source_id":0,"frame_num":977,"label":"go","blind_spot":"none","model":"lisa"},{"class_id":0,"confidence":0.2939,"x_center":0.9212,"y_center":0.4208,"width":0.0065,"height":0.0189,"source_id":0,"frame_num":977,"label":"go","blind_spot":"none","model":"lisa"},{"class_id":2,"confidence":0.8891,"x_center":0.68,"y_center":0.6045,"width":0.1978,"height":0.2326,"source_id":0,"frame_num":977,"label":"car","blind_spot":"none","model":"coco"},{"class_id":2,"confidence":0.7773,"x_center":0.3516,"y_center":0.5562,"width":0.0842,"height":0.1076,"source_id":0,"frame_num":977,"label":"car","blind_spot":"none","model":"coco"},{"class_id":2,"confidence":0.7627,"x_center":0.8024,"y_center":0.5819,"width":0.0478,"height":0.125,"source_id":0,"frame_num":977,"label":"car","blind_spot":"right","model":"coco"},{"class_id":2,"confidence":0.7494,"x_center":0.5005,"y_center":0.9189,"width":0.5569,"height":0.1469,"source_id":0,"frame_num":977,"label":"car","blind_spot":"none","model":"coco"},{"class_id":2,"confidence":0.7472,"x_center":0.8459,"y_center":0.5626,"width":0.0665,"height":0.0949,"source_id":0,"frame_num":977,"label":"car","blind_spot":"right","model":"coco"},{"class_id":2,"confidence":0.6939,"x_center":0.4277,"y_center":0.5592,"width":0.0346,"height":0.0485,"source_id":0,"frame_num":977,"label":"car","blind_spot":"none","model":"coco"},{"class_id":2,"confidence":0.4505,"x_center":0.3977,"y_center":0.551,"width":0.0288,"height":0.0652,"source_id":0,"frame_num":977,"label":"car","blind_spot":"none","model":"coco"},{"class_id":2,"confidence":0.44,"x_center":0.4647,"y_center":0.5649,"width":0.04,"height":0.0333,"source_id":0,"frame_num":977,"label":"car","blind_spot":"none","model":"coco"}]}